<AccessMath>
	<DataBase>
		<Name>LectureMath</Name>
		<OutputPaths> 
            <Temporal>temporal</Temporal>
            <Images>images</Images>
			<Videos>videos</Videos>
            <Annotations>annotations</Annotations>
			<Summaries>summaries</Summaries>			
        </OutputPaths>
		<Datasets>
			<Training>
				<LectureTitle>00000_000_001</LectureTitle>
				<LectureTitle>00000_000_003</LectureTitle>
				<LectureTitle>00000_001_001</LectureTitle>
				<LectureTitle>00000_001_006</LectureTitle>
				<LectureTitle>00000_001_009</LectureTitle>
				<LectureTitle>00000_001_018</LectureTitle>
				<LectureTitle>00000_001_012</LectureTitle>
				<LectureTitle>00005_020_013</LectureTitle>
				<LectureTitle>00005_027_011</LectureTitle>
				<LectureTitle>00008_032_024</LectureTitle>
				<LectureTitle>00009_006_004</LectureTitle>
				<LectureTitle>00010_001_001</LectureTitle>
				<LectureTitle>00011_030_011</LectureTitle>
				<LectureTitle>00012_006_003</LectureTitle>
				<LectureTitle>00012_018_032</LectureTitle>
				<LectureTitle>00013_005_019</LectureTitle>
				<LectureTitle>00013_005_080</LectureTitle>
			</Training>
			<Testing>
				<LectureTitle>00000_000_002</LectureTitle>
				<LectureTitle>00000_000_005</LectureTitle>
				<LectureTitle>00000_001_002</LectureTitle>
				<LectureTitle>00000_001_007</LectureTitle>
				<LectureTitle>00000_001_008</LectureTitle>
				<LectureTitle>00000_001_010</LectureTitle>
				<LectureTitle>00000_001_015</LectureTitle>
				<LectureTitle>00005_002_009</LectureTitle>
				<LectureTitle>00005_011_010</LectureTitle>
				<LectureTitle>00008_001_020</LectureTitle>
				<LectureTitle>00009_007_074</LectureTitle>
				<LectureTitle>00010_002_004</LectureTitle>
				<LectureTitle>00011_031_003</LectureTitle>
				<LectureTitle>00012_008_004</LectureTitle>
				<LectureTitle>00012_018_002</LectureTitle>
				<LectureTitle>00013_001_088</LectureTitle>
				<LectureTitle>00013_001_026</LectureTitle>
			</Testing>			
		</Datasets>
		<OldDatasets>
			<AM2015_Training>
				<LectureTitle>00000_000_001</LectureTitle>
				<LectureTitle>00000_000_003</LectureTitle>
				<LectureTitle>00000_001_001</LectureTitle>
				<LectureTitle>00000_001_006</LectureTitle>
				<LectureTitle>00000_001_018</LectureTitle>
			</AM2015_Training>
			<AM2015_Testing>
				<LectureTitle>00000_000_002</LectureTitle>
				<LectureTitle>00000_000_005</LectureTitle>
				<LectureTitle>00000_001_002</LectureTitle>
				<LectureTitle>00000_001_007</LectureTitle>
				<LectureTitle>00000_001_008</LectureTitle>
				<LectureTitle>00000_001_010</LectureTitle>
				<LectureTitle>00000_001_015</LectureTitle>
			</AM2015_Testing>
		</OldDatasets>
		<Lectures>
			<Lecture>
                <Id>00000_000_001</Id>
                <Title>00000_000_001</Title>
				<SourceID>00000</SourceID>
                <Parameters>
					<ForceResolution>
						<Width>1920</Width>
						<Height>1080</Height>
					</ForceResolution>
				</Parameters>
                <MetaData>
                    <Link>https://www.youtube.com/watch?v=6arlCAT3Hb4</Link>
                    <RawTitle>AccessMath - NM Lecture 01</RawTitle>					
                </MetaData>
                <Videos>
                    <Main>
                        <Video>
                            <Path>00000_000_001.mp4</Path>
                        </Video>                        
                    </Main>                    
                </Videos>     
                <AudioStreams></AudioStreams>
                <Transcriptions>                    
                </Transcriptions>                     
            </Lecture>
			<Lecture>
                <Id>00000_000_002</Id>
                <Title>00000_000_002</Title>
				<SourceID>00000</SourceID>
                <Parameters>
					<ForceResolution>
						<Width>1920</Width>
						<Height>1080</Height>
					</ForceResolution>
				</Parameters>
                <MetaData>
                    <Link>https://www.youtube.com/watch?v=AsDfluoYB4Q</Link>
                    <RawTitle>AccessMath - NM Lecture 02</RawTitle>
                </MetaData>
                <Videos>
                    <Main>
                        <Video>
                            <Path>00000_000_002.mp4</Path>
                        </Video>                        
                    </Main>                    
                </Videos>     
                <AudioStreams></AudioStreams>
                <Transcriptions>                    
                </Transcriptions>                     
            </Lecture>
			<Lecture>
                <Id>00000_000_003</Id>
                <Title>00000_000_003</Title>
				<SourceID>00000</SourceID>
                <Parameters>
					<ForceResolution>
						<Width>1920</Width>
						<Height>1080</Height>
					</ForceResolution>
				</Parameters>
                <MetaData>
                    <Link>https://www.youtube.com/watch?v=iggO022ncy8</Link>
                    <RawTitle>AccessMath - NM Lecture 03</RawTitle>
                </MetaData>
                <Videos>
                    <Main>
                        <Video>
                            <Path>00000_000_003.mp4</Path>
                        </Video>                        
                    </Main>                    
                </Videos>     
                <AudioStreams></AudioStreams>
                <Transcriptions>                    
                </Transcriptions>                     
            </Lecture>
			<Lecture>
                <Id>00000_000_005</Id>
                <Title>00000_000_005</Title>
				<SourceID>00000</SourceID>
                <Parameters>
					<ForceResolution>
						<Width>1920</Width>
						<Height>1080</Height>
					</ForceResolution>
				</Parameters>
                <MetaData>
                    <Link>https://www.youtube.com/watch?v=ar1eRRoRYBo</Link>
                    <RawTitle>AccessMath - NM Lecture 05</RawTitle>
                </MetaData>
                <Videos>
                    <Main>
                        <Video>
                            <Path>00000_000_005.mp4</Path>
                        </Video>                        
                    </Main>                    
                </Videos>     
                <AudioStreams></AudioStreams>
                <Transcriptions>                    
                </Transcriptions>                     
            </Lecture>
			<Lecture>
                <Id>00000_001_001</Id>
                <Title>00000_001_001</Title>
				<SourceID>00000</SourceID>
                <Parameters>
					<ForceResolution>
						<Width>1920</Width>
						<Height>1080</Height>
					</ForceResolution>
				</Parameters>
                <MetaData>
                    <Link>https://www.youtube.com/watch?v=Gyagxo3UTXo</Link>
                    <RawTitle>AccessMath - Lecture 01</RawTitle>
                </MetaData>
                <Videos>
                    <Main>
                        <Video>
                            <Path>00000_001_001.mp4</Path>
                        </Video>                        
                    </Main>                    
                </Videos>     
                <AudioStreams></AudioStreams>
                <Transcriptions>                    
                </Transcriptions>                     
            </Lecture>
			<Lecture>
                <Id>00000_001_002</Id>
                <Title>00000_001_002</Title>
				<SourceID>00000</SourceID>
                <Parameters>
					<ForceResolution>
						<Width>1920</Width>
						<Height>1080</Height>
					</ForceResolution>
				</Parameters>
                <MetaData>
                    <Link>https://www.youtube.com/watch?v=MDvbJi9X_XU</Link>
                    <RawTitle>AccessMath - Lecture 02</RawTitle>
                </MetaData>
                <Videos>
                    <Main>
                        <Video>
                            <Path>00000_001_002.mp4</Path>
                        </Video>                        
                    </Main>                    
                </Videos>     
                <AudioStreams></AudioStreams>
                <Transcriptions>                    
                </Transcriptions>                     
            </Lecture>
			<Lecture>
                <Id>00000_001_006</Id>
                <Title>00000_001_006</Title>
				<SourceID>00000</SourceID>
                <Parameters>
					<ForceResolution>
						<Width>1920</Width>
						<Height>1080</Height>
					</ForceResolution>
				</Parameters>
                <MetaData>
                    <Link>https://www.youtube.com/watch?v=YW8b2Nvt9dE</Link>
                    <RawTitle>AccessMath - Lecture 06</RawTitle>
                </MetaData>
                <Videos>
                    <Main>
                        <Video>
                            <Path>00000_001_006.mp4</Path>
                        </Video>                        
                    </Main>                    
                </Videos>     
                <AudioStreams></AudioStreams>
                <Transcriptions>                    
                </Transcriptions>                     
            </Lecture>
			<Lecture>
                <Id>00000_001_007</Id>
                <Title>00000_001_007</Title>
				<SourceID>00000</SourceID>
                <Parameters>
					<ForceResolution>
						<Width>1920</Width>
						<Height>1080</Height>
					</ForceResolution>
				</Parameters>
                <MetaData>
                    <Link>https://www.youtube.com/watch?v=SuWuHp0ZjPk</Link>
                    <RawTitle>AccessMath - Lecture 07</RawTitle>
                </MetaData>
                <Videos>
                    <Main>
                        <Video>
                            <Path>00000_001_007.mp4</Path>
                        </Video>                        
                    </Main>                    
                </Videos>     
                <AudioStreams></AudioStreams>
                <Transcriptions>                    
                </Transcriptions>                     
            </Lecture>
			<Lecture>
                <Id>00000_001_008</Id>
                <Title>00000_001_008</Title>
				<SourceID>00000</SourceID>
                <Parameters>
					<ForceResolution>
						<Width>1920</Width>
						<Height>1080</Height>
					</ForceResolution>
				</Parameters>
                <MetaData>
                    <Link>https://www.youtube.com/watch?v=7D8-R-4Cdfg</Link>
                    <RawTitle>AccessMath - Lecture 08</RawTitle>
                </MetaData>
                <Videos>
                    <Main>
                        <Video>
                            <Path>00000_001_008.mp4</Path>
                        </Video>                        
                    </Main>                    
                </Videos>     
                <AudioStreams></AudioStreams>
                <Transcriptions>                    
                </Transcriptions>                     
            </Lecture>
			<Lecture>
                <Id>00000_001_009</Id>
                <Title>00000_001_009</Title>
				<SourceID>00000</SourceID>
                <Parameters>
					<ForceResolution>
						<Width>1920</Width>
						<Height>1080</Height>
					</ForceResolution>
				</Parameters>
                <MetaData>
                    <Link>https://www.youtube.com/watch?v=3BNgzStHh2U</Link>
                    <RawTitle>AccessMath - Lecture 09</RawTitle>
                </MetaData>
                <Videos>
                    <Main>
                        <Video>
                            <Path>00000_001_009.mp4</Path>
                        </Video>                        
                    </Main>                    
                </Videos>     
                <AudioStreams></AudioStreams>
                <Transcriptions>                    
                </Transcriptions>                     
            </Lecture>
			<Lecture>
                <Id>00000_001_010</Id>
                <Title>00000_001_010</Title>
				<SourceID>00000</SourceID>
                <Parameters>
					<ForceResolution>
						<Width>1920</Width>
						<Height>1080</Height>
					</ForceResolution>
				</Parameters>
                <MetaData>
                    <Link>https://www.youtube.com/watch?v=TtS5EG8Dc-E</Link>
                    <RawTitle>AccessMath - Lecture 10</RawTitle>
                </MetaData>
                <Videos>
                    <Main>
                        <Video>
                            <Path>00000_001_010.mp4</Path>
                        </Video>                        
                    </Main>                    
                </Videos>     
                <AudioStreams></AudioStreams>
                <Transcriptions>                    
                </Transcriptions>                     
            </Lecture>
			<Lecture>
                <Id>00000_001_012</Id>
                <Title>00000_001_012</Title>
				<SourceID>00000</SourceID>
                <Parameters>
					<ForceResolution>
						<Width>1920</Width>
						<Height>1080</Height>
					</ForceResolution>
				</Parameters>
                <MetaData>
                    <Link>https://www.youtube.com/watch?v=ao6UZG8owlo</Link>
                    <RawTitle>AccessMath - Lecture 12</RawTitle>
                </MetaData>
                <Videos>
                    <Main>
                        <Video>
                            <Path>00000_001_012.mp4</Path>
                        </Video>                        
                    </Main>                    
                </Videos>     
                <AudioStreams></AudioStreams>
                <Transcriptions>                    
                </Transcriptions>                     
            </Lecture>
			<Lecture>
                <Id>00000_001_015</Id>
                <Title>00000_001_015</Title>
				<SourceID>00000</SourceID>
                <Parameters>
					<ForceResolution>
						<Width>1920</Width>
						<Height>1080</Height>
					</ForceResolution>
				</Parameters>
                <MetaData>
                    <Link>https://www.youtube.com/watch?v=Ctg9_qxk2Hg</Link>
                    <RawTitle>AccessMath - Lecture 15</RawTitle>
                </MetaData>
                <Videos>
                    <Main>
                        <Video>
                            <Path>00000_001_015.mp4</Path>
                        </Video>                        
                    </Main>                    
                </Videos>     
                <AudioStreams></AudioStreams>
                <Transcriptions>                    
                </Transcriptions>                     
            </Lecture>
			<Lecture>
                <Id>00000_001_018</Id>
                <Title>00000_001_018</Title>
				<SourceID>00000</SourceID>
                <Parameters>
					<ForceResolution>
						<Width>1920</Width>
						<Height>1080</Height>
					</ForceResolution>
				</Parameters>
                <MetaData>
                    <Link>https://www.youtube.com/watch?v=VTfBT_abSPw</Link>
                    <RawTitle>AccessMath - Lecture 18</RawTitle>
                </MetaData>
                <Videos>
                    <Main>
                        <Video>
                            <Path>00000_001_018.mp4</Path>
                        </Video>                        
                    </Main>                    
                </Videos>     
                <AudioStreams></AudioStreams>
                <Transcriptions>                    
                </Transcriptions>                     
            </Lecture>
			<Lecture>
                <Id>00001_000_036</Id>
                <Title>00001_000_036</Title>
				<SourceID>00001</SourceID>
                <Parameters>
					<ForceResolution>
						<Width>1280</Width>
						<Height>720</Height>
					</ForceResolution>
				</Parameters>
                <MetaData>
                    <Link>http://www.youtube.com/watch?v=3f9Ks4OBA0Y</Link>
                    <RawTitle>Raíz cúbica</RawTitle>
                </MetaData>
                <Videos>
                    <Main>
                        <Video>
                            <Path>00001_000_036.mp4</Path>
                        </Video>                        
                    </Main>                    
                </Videos>     
                <AudioStreams></AudioStreams>
                <Transcriptions>
                    <Spanish>00001_000_036.srt</Spanish>            
                </Transcriptions>                     
            </Lecture>
            <Lecture>
                <Id>00001_000_030</Id>
                <Title>00001_000_030</Title>
				<SourceID>00001</SourceID>
                <Parameters>
					<ForceResolution>
						<Width>1280</Width>
						<Height>720</Height>
					</ForceResolution>
				</Parameters>
                <MetaData>
                    <Link>http://www.youtube.com/watch?v=HbfECtikvzk</Link>
                    <RawTitle>Problemas con operaciones básicas</RawTitle>
                </MetaData>
                <Videos>
                    <Main>
                        <Video>
                            <Path>00001_000_030.mp4</Path>
                        </Video>                        
                    </Main>                    
                </Videos>     
                <AudioStreams></AudioStreams>                
            </Lecture>
			<Lecture>
                <Id>00001_006_016</Id>
                <Title>00001_006_016</Title>
				<SourceID>00001</SourceID>
                <Parameters></Parameters>
                <MetaData>
                    <Link>http://www.youtube.com/watch?v=j-cBaGNyHGA</Link>
                    <RawTitle>✅ Clasificación de los Números Reales │ Resta entre un Irracional y un Racional</RawTitle>
                </MetaData>
                <Videos>
                    <Main>
                        <Video>
                            <Path>00001_006_016.mp4</Path>
                        </Video>                        
                    </Main>                    
                </Videos>     
                <AudioStreams></AudioStreams>
                <Transcriptions>
                    <Spanish>00001_000_036.srt</Spanish>            
                </Transcriptions>                     
            </Lecture>
			<Lecture>
                <Id>00001_007_026</Id>
                <Title>00001_007_026</Title>
				<SourceID>00001</SourceID>
                <Parameters></Parameters>
                <MetaData>
                    <Link>http://www.youtube.com/watch?v=OXYxfZ5omc0</Link>
                    <RawTitle>✅ Operaciones Combinadas con Fracciones │ ejercicio 1</RawTitle>
                </MetaData>
                <Videos>
                    <Main>
                        <Video>
                            <Path>00001_007_026.mp4</Path>
                        </Video>                        
                    </Main>                    
                </Videos>     
                <AudioStreams></AudioStreams>
                <Transcriptions>
                    <Spanish>00001_007_026.srt</Spanish>            
                </Transcriptions>                     
            </Lecture>
			<Lecture>
                <Id>00001_002_006</Id>
                <Title>00001_002_006</Title>
				<SourceID>00001</SourceID>
                <Parameters>
					<ForceResolution>
						<Width>1280</Width>
						<Height>720</Height>
					</ForceResolution>
				</Parameters>
                <MetaData>
                    <Link>https://www.youtube.com/watch?v=JLREEDHR-zU</Link>
                    <RawTitle>Potenciación</RawTitle>
                </MetaData>
                <Videos>
                    <Main>
                        <Video>
                            <Path>00001_002_006.mp4</Path>
                        </Video>                        
                    </Main>                    
                </Videos>     
                <AudioStreams></AudioStreams>
                <Transcriptions>
                    <Spanish>00001_002_006.srt</Spanish>            
                </Transcriptions>                     
            </Lecture>
			<Lecture>
                <Id>00001_005_002</Id>
                <Title>00001_005_002</Title>
				<SourceID>00001</SourceID>
                <Parameters>
					<ForceResolution>
						<Width>1280</Width>
						<Height>720</Height>
					</ForceResolution>
				</Parameters>
                <MetaData>
                    <Link>https://www.youtube.com/watch?v=hKgBsBbMuW8</Link>
                    <RawTitle>Númeración Romana</RawTitle>
                </MetaData>
                <Videos>
                    <Main>
                        <Video>
                            <Path>00001_005_002.mp4</Path>
                        </Video>                        
                    </Main>                    
                </Videos>     
                <AudioStreams></AudioStreams>
                <Transcriptions>
                    <Spanish>00001_005_002.srt</Spanish>            
                </Transcriptions>                     
            </Lecture>
			<Lecture>
                <Id>00002_006_017</Id>
                <Title>00002_006_017</Title>
				<SourceID>00002</SourceID>
                <Parameters>
					<ForceResolution>
						<Width>1280</Width>
						<Height>720</Height>
					</ForceResolution>
				</Parameters>
                <MetaData>
                    <Link>http://www.youtube.com/watch?v=0JcFJyrk9gY</Link>
                    <RawTitle>NCERT 12 Maths Ex 5.Misc. (Part 1) Ch 5 Continuity &amp;amp; Differentiability hints &amp;amp; solutions</RawTitle>
                </MetaData>
                <Videos>
                    <Main>
                        <Video>
                            <Path>00002_006_017.mp4</Path>
                        </Video>                        
                    </Main>                    
                </Videos>     
                <AudioStreams></AudioStreams>                
            </Lecture>   
			<Lecture>
                <Id>00002_008_001</Id>
                <Title>00002_008_001</Title>
				<SourceID>00002</SourceID>
                <Parameters>
					<ForceResolution>
						<Width>1280</Width>
						<Height>720</Height>
					</ForceResolution>
				</Parameters>
                <MetaData>
                    <Link>http://www.youtube.com/watch?v=L61hIm_WoC8</Link>
                    <RawTitle>Basics, Order and Degree of Differential Equations|CBSE 12 Maths NCERT  Ex 9.1 intro</RawTitle>
                </MetaData>
                <Videos>
                    <Main>
                        <Video>
                            <Path>00002_008_001.mp4</Path>
                        </Video>                        
                    </Main>                    
                </Videos>     
                <AudioStreams></AudioStreams>                
            </Lecture>
			<Lecture>
                <Id>00003_003_003</Id>
                <Title>00003_003_003</Title>
				<SourceID>00003</SourceID>
                <Parameters>
					<ForceResolution>
						<Width>1280</Width>
						<Height>720</Height>
					</ForceResolution>
				</Parameters>
                <MetaData>
                    <Link>http://www.youtube.com/watch?v=apsLKTu5zRw</Link>
                    <RawTitle>Efeitos da corrente elétrica | químico térmico magnético fisiológico - Mãozinha em Física 118</RawTitle>
                </MetaData>
                <Videos>
                    <Main>
                        <Video>
                            <Path>00003_003_003.mp4</Path>
                        </Video>                        
                    </Main>                    
                </Videos>     
                <AudioStreams></AudioStreams>                
            </Lecture>
			<Lecture>
                <Id>00003_006_006</Id>
                <Title>00003_006_006</Title>
				<SourceID>00003</SourceID>
                <Parameters>
					<ForceResolution>
						<Width>1280</Width>
						<Height>720</Height>
					</ForceResolution>
				</Parameters>
                <MetaData>
                    <Link>http://www.youtube.com/watch?v=f14S6m5jRVI</Link>
                    <RawTitle>Dilatação Superficial (área) - Mãozinha em Física 036</RawTitle>
                </MetaData>
                <Videos>
                    <Main>
                        <Video>
                            <Path>00003_006_006.mp4</Path>
                        </Video>                        
                    </Main>                    
                </Videos>     
                <AudioStreams></AudioStreams>                
            </Lecture>
			<Lecture>
                <Id>00004_002_016</Id>
                <Title>00004_002_016</Title>
				<SourceID>00004</SourceID>
                <Parameters></Parameters>
                <MetaData>
                    <Link>http://www.youtube.com/watch?v=YnC4KtjGijw</Link>
                    <RawTitle>Función Inyectiva, Sobreyectiva y Biyectiva - Ejercicios Resueltos</RawTitle>
                </MetaData>
                <Videos>
                    <Main>
                        <Video>
                            <Path>00004_002_016.mp4</Path>
                        </Video>                        
                    </Main>                    
                </Videos>     
                <AudioStreams></AudioStreams>                
            </Lecture>
			<Lecture>
                <Id>00004_005_001</Id>
                <Title>00004_005_001</Title>
				<SourceID>00004</SourceID>
                <Parameters>
					<ForceResolution>
						<Width>1280</Width>
						<Height>720</Height>
					</ForceResolution>
				</Parameters>
                <MetaData>
                    <Link>http://www.youtube.com/watch?v=gl9EEbT7viM</Link>
                    <RawTitle>Población y Muestra - Ejemplos y Ejercicios Resueltos</RawTitle>
                </MetaData>
                <Videos>
                    <Main>
                        <Video>
                            <Path>00004_005_001.mp4</Path>
                        </Video>                        
                    </Main>                    
                </Videos>     
                <AudioStreams></AudioStreams>                
            </Lecture>
			<Lecture>
                <Id>00004_006_001</Id>
                <Title>00004_006_001</Title>
				<SourceID>00004</SourceID>
                <Parameters></Parameters>
                <MetaData>
                    <Link>http://www.youtube.com/watch?v=jiceVfALmV0</Link>
                    <RawTitle>Media, Mediana y Moda - Ejemplos y Ejercicios Resueltos - Medidas de Tendencia Central</RawTitle>
                </MetaData>
                <Videos>
                    <Main>
                        <Video>
                            <Path>00004_006_001.mp4</Path>
                        </Video>                        
                    </Main>                    
                </Videos>     
                <AudioStreams></AudioStreams>                
            </Lecture>
			<Lecture>
                <Id>00004_009_035</Id>
                <Title>00004_009_035</Title>
				<SourceID>00004</SourceID>
                <Parameters>
					<ForceResolution>
						<Width>1280</Width>
						<Height>720</Height>
					</ForceResolution>
				</Parameters>
                <MetaData>
                    <Link>http://www.youtube.com/watch?v=Tn4ff5b4qUM</Link>
                    <RawTitle>Cronometría - Calendarios - Ejercicios Resueltos</RawTitle>
                </MetaData>
                <Videos>
                    <Main>
                        <Video>
                            <Path>00004_009_035.mp4</Path>
                        </Video>                        
                    </Main>                    
                </Videos>     
                <AudioStreams></AudioStreams>                
            </Lecture>
			<Lecture>
                <Id>00005_002_009</Id>
                <Title>00005_002_009</Title>
				<SourceID>00005</SourceID>
                <Parameters></Parameters>
                <MetaData>
                    <Link>http://www.youtube.com/watch?v=wxokzHigf7g</Link>
                    <RawTitle>Centroide de una Figura Irregular - Salvador FI</RawTitle>
                </MetaData>
                <Videos>
                    <Main>
                        <Video>
                            <Path>00005_002_009.mp4</Path>
                        </Video>                        
                    </Main>                    
                </Videos>     
                <AudioStreams></AudioStreams>                
            </Lecture>
			<Lecture>
                <Id>00005_011_010</Id>
                <Title>00005_011_010</Title>
				<SourceID>00005</SourceID>
                <Parameters></Parameters>
                <MetaData>
                    <Link>http://www.youtube.com/watch?v=O779owSqSdE</Link>
                    <RawTitle>Curso de Equilibrio de la Partícula en un Video - Fuerzas de Tensión y Peso de Cuerpos Suspendidos</RawTitle>
                </MetaData>
                <Videos>
                    <Main>
                        <Video>
                            <Path>00005_011_010.mp4</Path>
                        </Video>                        
                    </Main>                    
                </Videos>     
                <AudioStreams></AudioStreams>                
            </Lecture>
			<Lecture>
                <Id>00005_020_013</Id>
                <Title>00005_020_013</Title>
				<SourceID>00005</SourceID>
                <Parameters></Parameters>
                <MetaData>
                    <Link>http://www.youtube.com/watch?v=U1N0LINsINo</Link>
                    <RawTitle>Momento con Respecto a un Eje en 3 Dimensiones - Video # 300 - Estática</RawTitle>
                </MetaData>
                <Videos>
                    <Main>
                        <Video>
                            <Path>00005_020_013.mp4</Path>
                        </Video>                        
                    </Main>                    
                </Videos>     
                <AudioStreams></AudioStreams>                
            </Lecture>
			<Lecture>
                <Id>00005_027_011</Id>
                <Title>00005_027_011</Title>
				<SourceID>00005</SourceID>
                <Parameters></Parameters>
                <MetaData>
                    <Link>http://www.youtube.com/watch?v=x3o32DJZae8</Link>
                    <RawTitle>Separación de Variables en Ecuación Diferencial - Salvador FI</RawTitle>
                </MetaData>
                <Videos>
                    <Main>
                        <Video>
                            <Path>00005_027_011.mp4</Path>
                        </Video>                        
                    </Main>                    
                </Videos>     
                <AudioStreams></AudioStreams>                
            </Lecture>
			<Lecture>
                <Id>00006_002_041</Id>
                <Title>00006_002_041</Title>
				<SourceID>00006</SourceID>
                <Parameters></Parameters>
                <MetaData>
                    <Link>https://www.youtube.com/watch?v=-aa_SKr80Io</Link>
                    <RawTitle>TEOREMAS sobre LÍMITES - #11 Sustitución NO directa - Ejercicio #3</RawTitle>
                </MetaData>
                <Videos>
                    <Main>
                        <Video>
                            <Path>00006_002_041.mp4</Path>
                        </Video>                        
                    </Main>                    
                </Videos>     
                <AudioStreams></AudioStreams>                
            </Lecture>
			<Lecture>
                <Id>00006_009_015</Id>
                <Title>00006_009_015</Title>
				<SourceID>00006</SourceID>
                <Parameters></Parameters>
                <MetaData>
                    <Link>http://www.youtube.com/watch?v=Z44Vez_gOKY</Link>
                    <RawTitle>LENGUAJE C - #6 OPERADORES (Operadores lógicos)</RawTitle>
                </MetaData>
                <Videos>
                    <Main>
                        <Video>
                            <Path>00006_009_015.mp4</Path>
                        </Video>                        
                    </Main>                    
                </Videos>     
                <AudioStreams></AudioStreams>                
            </Lecture>
			<Lecture>
                <Id>00006_011_025</Id>
                <Title>00006_011_025</Title>
				<SourceID>00006</SourceID>
                <Parameters></Parameters>
                <MetaData>
                    <Link>http://www.youtube.com/watch?v=89_f_7orNjc</Link>
                    <RawTitle>REGLAS DEL ÁLGEBRA DE BOOLE - Regla #11</RawTitle>
                </MetaData>
                <Videos>
                    <Main>
                        <Video>
                            <Path>00006_011_025.mp4</Path>
                        </Video>                        
                    </Main>                    
                </Videos>     
                <AudioStreams></AudioStreams>                
            </Lecture>
			<Lecture>
                <Id>00006_012_022</Id>
                <Title>00006_012_022</Title>
				<SourceID>00006</SourceID>
                <Parameters></Parameters>
                <MetaData>
                    <Link>http://www.youtube.com/watch?v=zIFAoo70398</Link>
                    <RawTitle>Matrices #15 MULTIPLICACIÓN de MATRICES - Ejercicio #1 Matriz 2x2</RawTitle>
                </MetaData>
                <Videos>
                    <Main>
                        <Video>
                            <Path>00006_012_022.mp4</Path>
                        </Video>                        
                    </Main>                    
                </Videos>     
                <AudioStreams></AudioStreams>                
            </Lecture>
			<Lecture>
                <Id>00006_002_050</Id>
                <Title>00006_002_050</Title>
				<SourceID>00006</SourceID>
                <Parameters></Parameters>
                <MetaData>
                    <Link>https://www.youtube.com/watch?v=RCibbZii8QI</Link>
                    <RawTitle>DERIVADAS - #7 Derivada de una función en cualquier x - Ejercicio #3</RawTitle>
                </MetaData>
                <Videos>
                    <Main>
                        <Video>
                            <Path>00006_002_050.mp4</Path>
                        </Video>                        
                    </Main>                    
                </Videos>     
                <AudioStreams></AudioStreams>                
            </Lecture>
			<Lecture>
                <Id>00006_002_049</Id>
                <Title>00006_002_049</Title>
				<SourceID>00006</SourceID>
                <Parameters></Parameters>
                <MetaData>
                    <Link>https://www.youtube.com/watch?v=nw7s-KevAfg</Link>
                    <RawTitle>DERIVADAS - #6 Derivada de una función en un punto - Ejercicio #3</RawTitle>
                </MetaData>
                <Videos>
                    <Main>
                        <Video>
                            <Path>00006_002_049.mp4</Path>
                        </Video>                        
                    </Main>                    
                </Videos>     
                <AudioStreams></AudioStreams>                
            </Lecture>
			<Lecture>
                <Id>00007_008_004</Id>
                <Title>00007_008_004</Title>
				<SourceID>00007</SourceID>
                <Parameters></Parameters>
                <MetaData>
                    <Link>http://www.youtube.com/watch?v=j1nwW8eyD0Q</Link>
                    <RawTitle>Ecuaciones diferenciales lineales - no lineales</RawTitle>
                </MetaData>
                <Videos>
                    <Main>
                        <Video>
                            <Path>00007_008_004.mp4</Path>
                        </Video>                        
                    </Main>                    
                </Videos>     
                <AudioStreams></AudioStreams>                
            </Lecture>
			<Lecture>
                <Id>00007_008_006</Id>
                <Title>00007_008_006</Title>
				<SourceID>00007</SourceID>
                <Parameters></Parameters>
                <MetaData>
                    <Link>http://www.youtube.com/watch?v=WAYBZTQoVkI</Link>
                    <RawTitle>Verificar o comprobar la solución de una Ecuación Diferencial | Ejemplo 1</RawTitle>
                </MetaData>
                <Videos>
                    <Main>
                        <Video>
                            <Path>00007_008_006.mp4</Path>
                        </Video>                        
                    </Main>                    
                </Videos>     
                <AudioStreams></AudioStreams>                
            </Lecture>
			<Lecture>
                <Id>00007_008_008</Id>
                <Title>00007_008_008</Title>
				<SourceID>00007</SourceID>
                <Parameters></Parameters>
                <MetaData>
                    <Link>http://www.youtube.com/watch?v=jA8nVFz94eY</Link>
                    <RawTitle>Ecuaciones diferenciales de variables separables | Introducción</RawTitle>
                </MetaData>
                <Videos>
                    <Main>
                        <Video>
                            <Path>00007_008_008.mp4</Path>
                        </Video>                        
                    </Main>                    
                </Videos>     
                <AudioStreams></AudioStreams>                
            </Lecture>
			<Lecture>
                <Id>00007_008_021</Id>
                <Title>00007_008_021</Title>
				<SourceID>00007</SourceID>
                <Parameters></Parameters>
                <MetaData>
                    <Link>http://www.youtube.com/watch?v=h8JY9daqCBY</Link>
                    <RawTitle>Ecuaciones diferenciales Homogéneas | Introducción</RawTitle>
                </MetaData>
                <Videos>
                    <Main>
                        <Video>
                            <Path>00007_008_021.mp4</Path>
                        </Video>                        
                    </Main>                    
                </Videos>     
                <AudioStreams></AudioStreams>                
            </Lecture>
			<Lecture>
                <Id>00007_001_007</Id>
                <Title>00007_001_007</Title>
				<SourceID>00007</SourceID>
                <Parameters></Parameters>
                <MetaData>
                    <Link>https://www.youtube.com/watch?v=suSz9RXFNTs</Link>
                    <RawTitle>Cuartiles introducción | Qué son y como encontrarlos en datos sin agrupar</RawTitle>
                </MetaData>
                <Videos>
                    <Main>
                        <Video>
                            <Path>00007_001_007.mp4</Path>
                        </Video>                        
                    </Main>                    
                </Videos>     
                <AudioStreams></AudioStreams>                
            </Lecture>
			<Lecture>
                <Id>00007_020_031</Id>
                <Title>00007_020_031</Title>
				<SourceID>00007</SourceID>
                <Parameters></Parameters>
                <MetaData>
                    <Link>https://www.youtube.com/watch?v=Ms-TNayg-qI</Link>
                    <RawTitle>Inecuaciones Cuadráticas o Racionales | Introducción</RawTitle>
                </MetaData>
                <Videos>
                    <Main>
                        <Video>
                            <Path>00007_020_031.mp4</Path>
                        </Video>                        
                    </Main>                    
                </Videos>     
                <AudioStreams></AudioStreams>                
            </Lecture>
			<Lecture>
                <Id>00008_001_020</Id>
                <Title>00008_001_020</Title>
				<SourceID>00008</SourceID>
                <Parameters></Parameters>
                <MetaData>
                    <Link>http://www.youtube.com/watch?v=55qZiZmcDiQ</Link>
                    <RawTitle>Algebra - Ch. 0.6: Basic Concepts (20 of 36) Simplifying an Algebraic Expression (Mistake!!!)</RawTitle>
                </MetaData>
                <Videos>
                    <Main>
                        <Video>
                            <Path>00008_001_020.mp4</Path>
                        </Video>                        
                    </Main>                    
                </Videos>     
                <AudioStreams></AudioStreams>                
            </Lecture>
			<Lecture>
                <Id>00008_032_024</Id>
                <Title>00008_032_024</Title>
				<SourceID>00008</SourceID>
                <Parameters></Parameters>
                <MetaData>
                    <Link>http://www.youtube.com/watch?v=SfZa9Y0ZTfQ</Link>
                    <RawTitle>PreCalculus - Matrices &amp;amp; Matrix Applications (23 of 33) Finding the Inverse of a 3x3 Matrix</RawTitle>
                </MetaData>
                <Videos>
                    <Main>
                        <Video>
                            <Path>00008_032_024.mp4</Path>
                        </Video>                        
                    </Main>                    
                </Videos>     
                <AudioStreams></AudioStreams>                
            </Lecture>
			<Lecture>
                <Id>00009_006_004</Id>
                <Title>00009_006_004</Title>
				<SourceID>00009</SourceID>
                <Parameters></Parameters>
                <MetaData>
                    <Link>http://www.youtube.com/watch?v=AbHn39y8eUo</Link>
                    <RawTitle>Statistics Lecture 2.2:  Creating Frequency Distribution and Histograms</RawTitle>
                </MetaData>
                <Videos>
                    <Main>
                        <Video>
                            <Path>00009_006_004.mp4</Path>
                        </Video>                        
                    </Main>                    
                </Videos>     
                <AudioStreams></AudioStreams>                
            </Lecture>
			<Lecture>
                <Id>00009_007_074</Id>
                <Title>00009_007_074</Title>
				<SourceID>00009</SourceID>
                <Parameters></Parameters>
                <MetaData>
                    <Link>http://www.youtube.com/watch?v=KEBfTHN1X-w</Link>
                    <RawTitle>Operations with Negative Exponents (TTP Video 74)</RawTitle>
                </MetaData>
                <Videos>
                    <Main>
                        <Video>
                            <Path>00009_007_074.mp4</Path>
                        </Video>                        
                    </Main>                    
                </Videos>     
                <AudioStreams></AudioStreams>                
            </Lecture>
			<Lecture>
                <Id>00010_001_001</Id>
                <Title>00010_001_001</Title>
				<SourceID>00010</SourceID>
                <Parameters></Parameters>
                <MetaData>
                    <Link>http://www.youtube.com/watch?v=L5TNUbISxGs</Link>
                    <RawTitle>Writing Algebraic Expressions from Word Problems</RawTitle>
                </MetaData>
                <Videos>
                    <Main>
                        <Video>
                            <Path>00010_001_001.mp4</Path>
                        </Video>                        
                    </Main>                    
                </Videos>     
                <AudioStreams></AudioStreams>                
            </Lecture>
			<Lecture>
                <Id>00010_002_004</Id>
                <Title>00010_002_004</Title>
				<SourceID>00010</SourceID>
                <Parameters></Parameters>
                <MetaData>
                    <Link>http://www.youtube.com/watch?v=Q_jPziAVk84</Link>
                    <RawTitle>Solving Equations with 2 Absolute Value Functions or More</RawTitle>
                </MetaData>
                <Videos>
                    <Main>
                        <Video>
                            <Path>00010_002_004.mp4</Path>
                        </Video>                        
                    </Main>                    
                </Videos>     
                <AudioStreams></AudioStreams>                
            </Lecture>			
			<Lecture>
                <Id>00011_030_011</Id>
                <Title>00011_030_011</Title>
				<SourceID>00011</SourceID>
                <Parameters></Parameters>
                <MetaData>
                    <Link>http://www.youtube.com/watch?v=OAdaxzLDEZ8</Link>
                    <RawTitle>Ejercicios de Polinomios #3 - Factorizar polinomios</RawTitle>
                </MetaData>
                <Videos>
                    <Main>
                        <Video>
                            <Path>00011_030_011.mp4</Path>
                        </Video>                        
                    </Main>                    
                </Videos>     
                <AudioStreams></AudioStreams>                
            </Lecture>
			<Lecture>
                <Id>00011_031_003</Id>
                <Title>00011_031_003</Title>
				<SourceID>00011</SourceID>
                <Parameters></Parameters>
                <MetaData>
                    <Link>http://www.youtube.com/watch?v=FIXG9-vEByE</Link>
                    <RawTitle>Multiplicación de ángulos - Operaciones con ángulos #3</RawTitle>
                </MetaData>
                <Videos>
                    <Main>
                        <Video>
                            <Path>00011_031_003.mp4</Path>
                        </Video>                        
                    </Main>                    
                </Videos>     
                <AudioStreams></AudioStreams>                
            </Lecture>
			<Lecture>
                <Id>00012_006_003</Id>
                <Title>00012_006_003</Title>
				<SourceID>00012</SourceID>
                <Parameters></Parameters>
                <MetaData>
                    <Link>http://www.youtube.com/watch?v=4_4OhYCFitA</Link>
                    <RawTitle>Derivatives: The Chain Rule</RawTitle>
                </MetaData>
                <Videos>
                    <Main>
                        <Video>
                            <Path>00012_006_003.mp4</Path>
                        </Video>                        
                    </Main>                    
                </Videos>     
                <AudioStreams></AudioStreams>                
            </Lecture>
			<Lecture>
                <Id>00012_008_004</Id>
                <Title>00012_008_004</Title>
				<SourceID>00012</SourceID>
                <Parameters></Parameters>
                <MetaData>
                    <Link>http://www.youtube.com/watch?v=VGw5_1FVk0I</Link>
                    <RawTitle>Trigonometry: Verifying Identities</RawTitle>
                </MetaData>
                <Videos>
                    <Main>
                        <Video>
                            <Path>00012_008_004.mp4</Path>
                        </Video>                        
                    </Main>                    
                </Videos>     
                <AudioStreams></AudioStreams>                
            </Lecture>
			<Lecture>
                <Id>00012_018_002</Id>
                <Title>00012_018_002</Title>
				<SourceID>00012</SourceID>
                <Parameters></Parameters>
                <MetaData>
                    <Link>http://www.youtube.com/watch?v=2B-uTNvJCb0</Link>
                    <RawTitle>Worldwide Differential Equations Section 2.1 #4</RawTitle>
                </MetaData>
                <Videos>
                    <Main>
                        <Video>
                            <Path>00012_018_002.mp4</Path>
                        </Video>                        
                    </Main>                    
                </Videos>     
                <AudioStreams></AudioStreams>                
            </Lecture>
			<Lecture>
                <Id>00012_018_032</Id>
                <Title>00012_018_032</Title>
				<SourceID>00012</SourceID>
                <Parameters></Parameters>
                <MetaData>
                    <Link>http://www.youtube.com/watch?v=0nRtui_rJnU</Link>
                    <RawTitle>Worldwide Differential Equations 4.4 #4f</RawTitle>
                </MetaData>
                <Videos>
                    <Main>
                        <Video>
                            <Path>00012_018_032.mp4</Path>
                        </Video>                        
                    </Main>                    
                </Videos>     
                <AudioStreams></AudioStreams>                
            </Lecture>
			<Lecture>
                <Id>00013_001_088</Id>
                <Title>00013_001_088</Title>
				<SourceID>00013</SourceID>
                <Parameters></Parameters>
                <MetaData>
                    <Link>http://www.youtube.com/watch?v=Ginor2tP16o</Link>
                    <RawTitle>SIMPLIFICACIÓN DE EXPRESIONES CON POTENCIAS - Ejercicio 3</RawTitle>
                </MetaData>
                <Videos>
                    <Main>
                        <Video>
                            <Path>00013_001_088.mp4</Path>
                        </Video>                        
                    </Main>                    
                </Videos>     
                <AudioStreams></AudioStreams>                
            </Lecture>
			<Lecture>
                <Id>00013_005_019</Id>
                <Title>00013_005_019</Title>
				<SourceID>00013</SourceID>
                <Parameters></Parameters>
                <MetaData>
                    <Link>https://www.youtube.com/watch?v=h0A49mUqLvk</Link>
                    <RawTitle>LÍMITES ALGEBRAICOS - Ejercicio</RawTitle>
                </MetaData>
                <Videos>
                    <Main>
                        <Video>
                            <Path>00013_005_019.mp4</Path>
                        </Video>                        
                    </Main>                    
                </Videos>     
                <AudioStreams></AudioStreams>                
            </Lecture>
			<Lecture>
                <Id>00013_005_080</Id>
                <Title>00013_005_080</Title>
				<SourceID>00013</SourceID>
                <Parameters></Parameters>
                <MetaData>
                    <Link>http://www.youtube.com/watch?v=vMd4Gogj37Q</Link>
                    <RawTitle>DERIVACIÓN DE FUNCIONES - Ejercicio 23</RawTitle>
                </MetaData>
                <Videos>
                    <Main>
                        <Video>
                            <Path>00013_005_080.mp4</Path>
                        </Video>                        
                    </Main>                    
                </Videos>     
                <AudioStreams></AudioStreams>                
            </Lecture>
			<Lecture>
                <Id>00013_001_026</Id>
                <Title>00013_001_026</Title>
				<SourceID>00013</SourceID>
                <Parameters></Parameters>
                <MetaData>
                    <Link>http://www.youtube.com/watch?v=4utrfzZ_BfY</Link>
                    <RawTitle>PRODUCTOS NOTABLES: SUMA POR DIFERENCIA (Ejercicio 3)</RawTitle>
                </MetaData>
                <Videos>
                    <Main>
                        <Video>
                            <Path>00013_001_026.mp4</Path>
                        </Video>                        
                    </Main>                    
                </Videos>     
                <AudioStreams></AudioStreams>                
            </Lecture>
		</Lectures>
	</DataBase>
</AccessMath>